odoo/addons/stock_portal_lot_list_download/README.rst
odoo/addons/stock_portal_lot_list_download/__init__.py
odoo/addons/stock_portal_lot_list_download/__manifest__.py
odoo/addons/stock_portal_lot_list_download/controllers/__init__.py
odoo/addons/stock_portal_lot_list_download/controllers/portal.py
odoo/addons/stock_portal_lot_list_download/i18n/it.po
odoo/addons/stock_portal_lot_list_download/i18n/stock_portal_lot_list_download.pot
odoo/addons/stock_portal_lot_list_download/readme/CONTRIBUTORS.md
odoo/addons/stock_portal_lot_list_download/readme/DESCRIPTION.md
odoo/addons/stock_portal_lot_list_download/readme/USAGE.md
odoo/addons/stock_portal_lot_list_download/static/description/icon.png
odoo/addons/stock_portal_lot_list_download/static/description/index.html
odoo/addons/stock_portal_lot_list_download/tests/__init__.py
odoo/addons/stock_portal_lot_list_download/tests/test_stock_portal_lot_list_download.py
odoo/addons/stock_portal_lot_list_download/views/sale_stock_portal_template.xml
odoo_addon_stock_portal_lot_list_download-18.0.1.0.0.2.dist-info/METADATA
odoo_addon_stock_portal_lot_list_download-18.0.1.0.0.2.dist-info/WHEEL
odoo_addon_stock_portal_lot_list_download-18.0.1.0.0.2.dist-info/top_level.txt
odoo_addon_stock_portal_lot_list_download-18.0.1.0.0.2.dist-info/RECORD
